beekeeper/observers/watsonx/__init__.py
beekeeper/observers/watsonx/base.py
beekeeper/observers/watsonx/instrumentation.py
beekeeper_observers_watsonx-1.0.3.dist-info/METADATA
beekeeper_observers_watsonx-1.0.3.dist-info/WHEEL
beekeeper_observers_watsonx-1.0.3.dist-info/RECORD
