Metadata-Version: 2.4
Name: beekeeper-observers-watsonx
Version: 1.0.3
Summary: beekeeper observers watsonx extension
Author-email: Leonardo Furnielis <leonardofurnielis@outlook.com>
License: Apache-2.0
Requires-Python: <4.0,>=3.10
Requires-Dist: beekeeper-core<2.0.0,>=1.0.0
Requires-Dist: certifi<2026.0.0,>=2025.4.26
Requires-Dist: ibm-aigov-facts-client<1.0.97,>=1.0.95
Requires-Dist: ibm-watson-openscale<3.1.0,>=3.0.49
Requires-Dist: ibm-watsonx-ai<2.0.0,>=1.3.26
Requires-Dist: ipython==8.37.0
Provides-Extra: dev
Requires-Dist: ruff>=0.11.13; extra == 'dev'
